wikiciteparser/__init__.py
wikiciteparser/bulk.py
wikiciteparser/cs1.lua
wikiciteparser/parser.py
wikiciteparser/tests.py
wikiciteparser/en/__init__.py
wikiciteparser/it/__init__.py
wikiciteparser-0.3.0.dist-info/METADATA
wikiciteparser-0.3.0.dist-info/WHEEL
wikiciteparser-0.3.0.dist-info/top_level.txt
wikiciteparser-0.3.0.dist-info/RECORD
