Metadata-Version: 2.1
Name: wikiciteparser
Version: 0.3.0
Summary: A parser for wikipedia citation templates
Home-page: https://github.com/dissemin/wikiciteparser
Author: Antonin Delpeuch
License: MIT
Keywords: wikipedia citation
Platform: UNKNOWN
Classifier: Development Status :: 3 - Alpha
Classifier: Intended Audience :: Developers
Classifier: Topic :: Text Processing :: Markup
Classifier: License :: OSI Approved :: MIT License
Classifier: Programming Language :: Python :: 3
Requires-Dist: lupa
Requires-Dist: mwparserfromhell
Requires-Dist: mwtypes
Requires-Dist: mwxml
